retinotopic_mapping/DisplayStimulus.py
retinotopic_mapping/MonitorSetup.py
retinotopic_mapping/RetinotopicMapping.py
retinotopic_mapping/StimulusRoutines.py
retinotopic_mapping/__init__.py
retinotopic_mapping/for_debugging.py
retinotopic_mapping/tools/FileTools.py
retinotopic_mapping/tools/ImageAnalysis.py
retinotopic_mapping/tools/PlottingTools.py
retinotopic_mapping/tools/__init__.py
retinotopic_mapping/tools/IO/__init__.py
retinotopic_mapping/tools/IO/nidaq.py
retinotopic_maps-2.0.0.dist-info/DESCRIPTION.rst
retinotopic_maps-2.0.0.dist-info/METADATA
retinotopic_maps-2.0.0.dist-info/RECORD
retinotopic_maps-2.0.0.dist-info/WHEEL
retinotopic_maps-2.0.0.dist-info/metadata.json
retinotopic_maps-2.0.0.dist-info/top_level.txt
