Metadata-Version: 2.0
Name: retinotopic-maps
Version: 2.0.0
Summary: retinotopic mapping tools
Home-page: https://github.com/zhuangjun1981/retinotopic_mapping
Author: Jun Zhuang @ Allen Institute for Brain Science
Author-email: junz@alleninstitute.org
License: UNKNOWN
Platform: any
Classifier: Programming Language :: Python
Classifier: Development Status :: 4 - Beta
Classifier: Natural Language :: English
Classifier: Operating System :: OS Independent
Requires-Dist: numpy
Requires-Dist: opencv-python
Requires-Dist: scikit-image
Requires-Dist: scipy
Requires-Dist: tifffile
